tester_gae/__init__.py
tester_gae-1.4.0.dist-info/LICENSE
tester_gae-1.4.0.dist-info/METADATA
tester_gae-1.4.0.dist-info/WHEEL
tester_gae-1.4.0.dist-info/top_level.txt
tester_gae-1.4.0.dist-info/RECORD
