Metadata-Version: 2.1
Name: tester-gae
Version: 1.4.0
Summary: Class for autotests GoogleAppEngine python apps
Home-page: https://github.com/vb64/test.helper.gae
Author: Vitaly Bogomolov
Author-email: mail@vitaly-bogomolov.ru
License: UNKNOWN
Download-URL: https://github.com/vb64/test.helper.gae/archive/v1.4.tar.gz
Keywords: python,Python27,GAE,GoogleAppEngine,unittest
Platform: UNKNOWN
Classifier: Programming Language :: Python :: 2.7
Classifier: License :: OSI Approved :: MIT License
Classifier: Operating System :: OS Independent
Requires-Dist: Pillow
Requires-Dist: gae-installer (>=1.9.54)
